{
  "welcome": "مرحبًا بك في دوس!",
  "enterAccount": "سجّل الدخول إلى حسابك للمتابعة",
  "phoneNumber": "رقم الجوال",
  "yourPhoneNumber": "أدخل رقم جوالك",
  "otpCode": "رمز التحقق",
  "enterOtp": "أدخل الرمز المكون من 4 أرقام",
  "requestOtp": "إرسال الرمز",
  "verifyOtp": "تحقق من الرمز",
  "rememberMe": "تذكرني",
  "forgetPassword": "نسيت كلمة المرور؟",
  "login": "تسجيل الدخول",
  "register": "إنشاء حساب",
  "dontHaveAccount": "ليس لديك حساب؟",
  "signUp": "إنشاء حساب جديد",
  "alreadyHaveAccount": "لديك حساب بالفعل؟",
  "signIn": "دخول",
  "Home": "الرئيسية",
  "Services": "الخدمات",
  "Reels": "المقاطع",
  "Messages": "الرسائل",
  "Account": "الحساب",
  "featuredCars": "السيارات المميزة",
  "seeAll": "عرض الكل",
  "carReels": "مقاطع السيارات",
  "viewAll": "عرض الكل",
  "availableCars": "السيارات المتاحة",
  "filter": "تصفية",
  "loadMore": "تحميل المزيد",
  "search": "بحث",
  "notifications": "الإشعارات",
  "profile": "الملف الشخصي",
  "settings": "الإعدادات",
  "logout": "تسجيل الخروج",
  "language": "اللغة",
  "english": "الإنجليزية",
  "arabic": "العربية",
  "English": "الإنجليزية",
  "Arabic": "العربية",
  "appType": "نوع الحساب",
  "chooseAccountType": "اختر نوع الحساب",
  "personalAccount": "حساب شخصي",
  "businessAccount": "حساب أعمال",
  "onboardingTitle1": "اعثر على سيارتك المثالية",
  "onboardingSubtitle1": "تصفح آلاف السيارات من وكلاء وأفراد موثوقين.",
  "onboardingTitle2": "احجز بثقة وسهولة",
  "onboardingSubtitle2": "احجز سيارتك بسهولة وأمان في خطوات بسيطة.",
  "onboardingTitle3": "دعم وأمان على مدار الساعة",
  "onboardingSubtitle3": "استمتع براحة البال مع دعمنا الدائم ومنصتنا الآمنة.",
  "getStarted": "ابدأ الآن",
  "skip": "تخطي",
  "next": "التالي",
  "email": "البريد الإلكتروني",
  "password": "كلمة المرور",
  "confirmPassword": "تأكيد كلمة المرور",
  "firstName": "الاسم الأول",
  "lastName": "اسم العائلة",
  "nickName": "الاسم المستعار",
  "dateOfBirth": "تاريخ الميلاد",
  "createAccount": "إنشاء حساب",
  "signInSuccess": "تم تسجيل الدخول بنجاح!",
  "accountCreated": "تم إنشاء الحساب بنجاح!",
  "otpSent": "تم إرسال رمز التحقق!",
  "otpVerified": "تم التحقق من الرمز بنجاح!",
  "pleaseEnterPhone": "يرجى إدخال رقم الجوال أولاً.",
  "operationFailed": "حدث خطأ، يرجى المحاولة مرة أخرى.",
  "resetPassword": "إعادة تعيين كلمة المرور",
  "newPassword": "كلمة مرور جديدة",
  "confirmNewPassword": "تأكيد كلمة المرور الجديدة",
  "send": "إرسال",
  "continue": "متابعة",
  "back": "رجوع",
  "submit": "تأكيد",
  "success": "نجاح",
  "error": "خطأ",
  "editProfile": "تعديل الملف الشخصي",
  "save": "حفظ",
  "changeLanguage": "تغيير اللغة",
  "addCar": "إضافة سيارة",
  "carDetails": "تفاصيل السيارة",
  "carImages": "صور السيارة",
  "reviewSubmit": "المراجعة والتأكيد",
  "yourName": "اسمك",
  "yourAddressLine": "عنوانك",
  "yourPostcode": "الرمز البريدي",
  "carBrand": "ماركة السيارة",
  "carModel": "موديل السيارة",
  "year": "السنة",
  "uploadCarImages": "رفع صور السيارة",
  "additionalNotes": "ملاحظات إضافية",
  "anyAdditionalNotes": "أي ملاحظات إضافية...",
  "pleaseReviewCarDetails": "يرجى مراجعة تفاصيل السيارة قبل التأكيد.",
  "carSummaryGoesHere": "ملخص السيارة يظهر هنا...",
  "OR": "أو",
  "welcomeBack": "مرحباً بعودتك",
  "readyToHitTheRoad": "مستعد للانطلاق على الطريق.",
  "welcomeBackFull": "مرحباً بعودتك\nمستعد للانطلاق على الطريق.",
  "fullName": "الاسم الكامل",
  "Fill Your Information": "أدخل معلوماتك",
  "Sign Up": "إنشاء حساب",
  "ForgotPassword": "هل نسيت كلمة المرور؟",
  "Verify your phone number": "تحقق من رقم الجوال",
  "We have sent you an SMS with a code to number": "لقد أرسلنا لك رمز التحقق على رقم الجوال",
  "Country": "البلد",
  "Phone Number": "رقم الهاتف",
  "Please enter your phone number": "يرجى إدخال رقم الهاتف",
  "Please enter a valid phone number": "يرجى إدخال رقم هاتف صحيح",
  "nearbyServices": "الخدمات القريبة",
  "locationPermissionRequired": "إذن الموقع مطلوب",
  "locationPermissionMessage": "نحتاج إلى موقعك لعرض الخدمات القريبة منك",
  "allowLocationAccess": "السماح بالوصول للموقع",
  "locationServicesDisabled": "خدمة الموقع معطلة",
  "locationServicesDisabledMessage": "يرجى تشغيل خدمة الموقع في إعدادات الجهاز لعرض الخدمات القريبة منك",
  "openSettings": "فتح الإعدادات",
  "locationPermissionDenied": "إذن الموقع مرفوض",
  "locationPermissionDeniedMessage": "يرجى السماح بالوصول إلى الموقع في إعدادات التطبيق لعرض الخدمات القريبة منك",
  "locationError": "خطأ في تحديد الموقع",
  "locationErrorMessage": "حدث خطأ أثناء تحديد موقعك. سيتم استخدام موقع افتراضي لعرض الخدمات.",
  "ok": "حسناً",
  "cancel": "إلغاء",
  "allow": "السماح",
  "noNearbyServices": "لا توجد خدمات قريبة",
  "noNearbyServicesMessage": "API يعيد قائمة فارغة - تحقق من البيانات في الخادم",
  "retry": "إعادة المحاولة",
  "showOnMap": "عرض على الخريطة",
  "moreDetails": "تفاصيل أكثر",
  "open": "مفتوح",
  "closed": "مغلق",
  "kmAway": "كم بعيداً",
  "all": "الكل",
  "mechanics": "ميكانيكي",
  "petrol": "بنزين",
  "openNow": "مفتوح الآن",
  "invalidPhoneNumber": "رقم هاتف غير صحيح",
  "searchCountry": "البحث عن بلد",
  "noCountryFound": "لم يتم العثور على بلد",
  "Reset your password": "إعادة تعيين كلمة المرور",
  "Enter your new password": "أدخل كلمة المرور الجديدة",
  "Enter verification code": "أدخل رمز التحقق",
  "We have send a Code to": "لقد أرسلنا لك رمز التحقق على رقم الجوال",
  "Create a": "إنشاء حساب",
  "New account ": "حساب جديد",
  "loading": "جاري التحميل...",
  "passwordsDoNotMatch": "كلمات المرور غير متطابقة",
  "username": "اسم المستخدم",
  "address": "العنوان",
  "serviceLocation": "موقع الخدمة",
  "getDirections": "احصل على الاتجاهات",
  "workingHours": "ساعات العمل",
  "contact": "اتصل بنا",
  "photos": "الصور",
  "aboutServiceProvider": "حول مزود الخدمة",
  "servicesAtLocation": "الخدمات في هذا الموقع",
  "verifiedByDubaiMunicipality": "موثق من بلدية دبي",
  "nearBusinessBayMetro": "قرب محطة مترو بيزنس باي - المخرج 2",
  "minutesDrive": "دقائق بالسيارة",
  "callNow": "اتصل الآن",
  "whatsapp": "واتساب",
  "chat": "محادثة",
  "engineCheck": "فحص المحرك",
  "oilChange": "تغيير الزيت",
  "brakeInspection": "فحص الفرامل",
  "acService": "خدمة التكييف",
  "servicesCompleted": "خدمات مكتملة",
  "activeSince": "نشط منذ",
  "All Items": "كل العناصر",
  "Cars": "السيارات",
  "Accessories": "الملحقات",
  "Recent": "الأخيرة",
  "Auto Dark Mode": "الوضع الداكن التلقائي",
  "Choose Your Theme": "اختر الثيم الخاص بك",
  "Switch automatically based on system settings": "التبديل تلقائيًا حسب إعدادات النظام",
  "Display Preferences": "تفضيلات العرض",
  "Font Size": "حجم الخط",
  "Adjust text size for better\\nreadability": "ضبط حجم النص لسهولة\\nالقراءة",
  "Dark Mode": "الوضع الداكن",
  "Account Settings": "إعدادات الحساب",
  "My Activity": "نشاطي",
  "Preferences": "تفضيلاتي",
  "Support": "الدعم",
  "Change Language": "تغيير اللغة",
  "Change Password": "تغيير كلمة المرور",
  "Edit Profile": "تعديل الملف الشخصي",
  "My Profile": "ملفي الشخصي",
  "Saved Items": "العناصر المحفوظة",
  "Notification Settings": "إعدادات الإشعارات",
  "Theme Settings": "إعدادات الثيم",
  "Apply Language": "تطبيق اللغة",
  "View Details": "عرض التفاصيل",
  "Apply Theme Settings": "تطبيق إعدادات الثيم",
  "Save Changes": "حفظ التغييرات",
  "Update Password": "تحديث كلمة المرور",
  "Language Change": "تغيير اللغة",
  "The app may need to restart to fully apply the new language settings.": "قد يحتاج التطبيق لإعادة التشغيل لتطبيق إعدادات اللغة الجديدة بالكامل.",
  "Current Password": "كلمة المرور الحالية",
  "Full Name": "الاسم الكامل",
  "Confirm New Password": "تأكيد كلمة المرور الجديدة",
  "Gmail (optional)": "جيميل (اختياري)",
  "Location (optional)": "الموقع (اختياري)",
  "At least 8 characters": "على الأقل 8 أحرف",
  "One uppercase letter": "حرف كبير واحد على الأقل",
  "One number": "رقم واحد على الأقل",
  "Weak": "ضعيف",
  "Medium": "متوسط",
  "Strong": "قوي",
  "Notification Methods": "طرق الإشعارات",
  "Preview": "معاينة",
  "App interface will appear in:": "واجهة التطبيق ستظهر بـ:",
  "Password Tips": "نصائح كلمة المرور",
  "Mix uppercase, lowercase, numbers and symbols": "اخلط الحروف الكبيرة والصغيرة والأرقام والرموز",
  "Avoid personal information like names or dates": "تجنب المعلومات الشخصية مثل الأسماء أو التواريخ",
  "General Notifications": "الإشعارات العامة",
  "Enable all notifications": "تفعيل جميع الإشعارات",
  "Push Notifications": "الإشعارات الفورية",
  "Receive notifications on your device": "تلقي الإشعارات على جهازك",
  "Email Notifications": "الإشعارات عبر البريد الإلكتروني",
  "Receive notifications via email": "تلقي الإشعارات عبر البريد الإلكتروني",
  "New Messages": "رسائل جديدة",
  "Get notified when you receive new\\nmessages": "تلقي إشعار عند وصول رسائل\\nجديدة",
  "Promotions": "عروض",
  "Special offers and promotional content": "عروض ومحتوى ترويجي خاص",
  "Listing Updates": "تحديثات القوائم",
  "Updates on your car listings and inquiries": "تحديثات على قوائم سياراتك والاستفسارات",
  "Security Notice": "تنبيه أمني",
  "For your security, we recommend changin your password regularly.": "لأمانك، نوصي بتغيير كلمة المرور بانتظام.",
  "Select Language": "اختر اللغة",
  "Choose your preferred language": "اختر لغتك المفضلة",
  "Saved Listings": "القوائم المحفوظة",
  "Log Out": "تسجيل الخروج",
  "Help Center": "مركز المساعدة",
  "Contact Support": "اتصل بالدعم",
  "Theme": "الثيم",
  "Notifications": "الإشعارات",
  "Your changes have been saved successfully.": "تم حفظ التغييرات بنجاح",
  "LogOut in Success": "تم تسجيل الخروج بنجاح!",
  "Retype your new password!": "اعد كتابة كلمة السر الجديدة!",
  "password_changed_success": "تم تغيير كلمة المرور بنجاح",
  "No saved items yet": "No saved items yet",
  "No items in this tab yet": "No items in this tab yet",
  "Phone number confirmed successfully": "تم تأكيد رقم الهاتف بنجاح",
  "Enter the verification code sent to": "أدخل رمز التحقق المرسل إلى",
  "Operation canceled": "تم إلغاء العملية",
  "OTP Verification": "التحقق برمز OTP",
  "Resend": "إعادة الإرسال",
  "didntReceiveCode": "لم تستلم الرمز؟",
  "Click to change your profile picture": "اضغط لتغيير صورة ملفك الشخصي",
  "Something went wrong": "حدث خطأ ما",
  "Select your preferred language": "اختر لغتك المفضلة",
  "languageChangeMessage": "قد يحتاج التطبيق إلى إعادة التشغيل لتطبيق إعدادات اللغة الجديدة بالكامل.",
  "selectLanguage": "اختر اللغة",
  "appLanguage": "لغة التطبيق",
  "systemDefault": "افتراضي النظام",
  "Sign Up as User": "تسجيل الدخول كمستخدم",
  "Confirmation Code": "رمز التاكيد",
  "deleteAccountTitle": "حذف الحساب",
  "currentPassword": "كلمة المرور الحالية",
  "deleteReason": "سبب حذف الحساب (اختياري)",
  "enterPasswordWarning": "الرجاء إدخال كلمة المرور",
  "deleteAccountButton": "حذف الحساب",
  "deleteAccountSuccess": "تم حذف الحساب بنجاح ✅",
  "deleteAccountError": "حدث خطأ أثناء حذف الحساب ❌",
  "deleteReason_betterApp": "وجدت تطبيق أفضل",
  "deleteReason_privacy": "مخاوف الخصوصية",
  "deleteReason_notifications": "عدد كبير من الإشعارات",
  "deleteReason_other": "أخرى",
  "privacyPolicy": "سياسة الخصوصية",
  "privacyPolicySubtitle": "خصوصيتك تهمنا",
  "introduction": "مقدمة",
  "introductionText": "مرحبًا بك في موقعنا. نحن نحترم خصوصيتك ونلتزم بحماية المعلومات التي تشاركها معنا. توضح سياسة الخصوصية هذه المعلومات التي نجمعها وكيف نستخدمها والخيارات المتاحة لك بخصوص معلوماتك.",
  "informationWeCollect": "المعلومات التي نجمعها",
  "informationWeCollectText": "• المعلومات التي تقدمها: مثل اسمك، عنوان بريدك الإلكتروني، رقم هاتفك، والمحتوى المقدم عبر النماذج أو التسجيل.\n\n• المعلومات التلقائية: بيانات الاستخدام مثل الصفحات التي تمت زيارتها، الوقت المستغرق، عنوان IP، نوع المتصفح، ومعلومات الجهاز.",
  "howWeUseInformation": "كيفية استخدام المعلومات",
  "howWeUseInformationText": "نستخدم معلوماتك لتحسين خدماتنا، والتواصل معك بخصوص حسابك أو استفساراتك، وإرسال إشعارات اختيارية أو مواد تسويقية إذا وافقت. نستخدم البيانات أيضًا لأغراض تحليلية وتقنية لتحسين أداء الموقع وتجربة المستخدم.",
  "locationInformation": "معلومات الموقع",
  "locationInformationText": "قد يطلب التطبيق الوصول إلى موقع جهازك لتقديم أفضل خدمة ممكنة. يساعدنا ذلك على تخصيص المحتوى، وتقديم توصيات بالخدمات، وتحسين تجربة المستخدم بناءً على موقعك.\n\nلا يتم مشاركة بيانات موقعك مع أطراف ثالثة لأغراض التسويق، وتُستخدم داخليًا فقط لتحسين وظائف التطبيق. يمكنك التحكم في الوصول إلى الموقع من إعدادات جهازك في أي وقت.",
  "informationSharing": "مشاركة المعلومات",
  "informationSharingText": "نحن لا نبيع معلوماتك الشخصية لأطراف ثالثة. قد نشارك بيانات محدودة مع مزودي خدمات موثوقين (مثل مزودي الاستضافة، أدوات التحليلات، ومعالجات الدفع) بموجب اتفاقيات سرية صارمة.",
  "cookies": "ملفات تعريف الارتباط",
  "cookiesText": "نستخدم ملفات تعريف الارتباط لتعزيز تجربة التصفح. يمكنك تعطيل ملفات تعريف الارتباط في إعدادات المتصفح، لكن قد يؤثر ذلك على بعض ميزات الموقع.",
  "dataSecurity": "أمن البيانات",
  "dataSecurityText": "نتخذ تدابير تقنية وتنظيمية معقولة لحماية بياناتك من الوصول غير المصرح به أو الفقدان. ومع ذلك، لا يوجد نظام آمن 100٪، لذا يرجى توخي الحذر عند مشاركة المعلومات الحساسة.",
  "dataRetention": "الاحتفاظ بالبيانات",
  "dataRetentionText": "نحتفظ بالبيانات فقط طالما كان ذلك ضروريًا لتحقيق الأغراض الموضحة أعلاه أو للامتثال للالتزامات القانونية.",
  "yourRights": "حقوقك",
  "yourRightsText": "• الحق في الوصول إلى بياناتك وطلب نسخة منها.\n• الحق في تصحيح البيانات غير الدقيقة.\n• الحق في طلب حذف بياناتك في ظروف معينة.\n• الحق في سحب الموافقة على معالجة البيانات إذا كانت الموافقة مطلوبة.",
  "linksToOtherSites": "روابط لمواقع أخرى",
  "linksToOtherSitesText": "قد يحتوي موقعنا على روابط لمواقع خارجية. نحن غير مسؤولين عن ممارسات الخصوصية لتلك المواقع ونشجعك على مراجعة سياساتها قبل مشاركة أي معلومات شخصية.",
  "changesToPolicy": "التغييرات في هذه السياسة",
  "changesToPolicyText": "نحتفظ بالحق في تحديث هذه السياسة من وقت لآخر. وسيتم دائمًا عرض تاريخ الإصدار الأخير في أعلى هذه الصفحة.",
  "unableToCreateChat": "تعذر إنشاء المحادثة: معرف التاجر غير صحيح",
  "creatingChat": "جاري إنشاء المحادثة...",
  "errorLoadingMessages": "خطأ في تحميل الرسائل",
  "noMessagesYet": "لا توجد رسائل بعد",
  "startConversation": "ابدأ محادثة",
  "unableToStartChat": "تعذر بدء المحادثة: معلومات البائع غير صحيحة",
  "failedToLoadChats": "فشل تحميل المحادثات",
  "failedToLoadMessages": "فشل تحميل الرسائل",
  "failedToSendMessage": "فشل إرسال الرسالة",
  "noAccessTokenFound": "لم يتم العثور على رمز الوصول",
  "notConnectedToChatServer": "غير متصل بخادم المحادثة",
  "failedToLoadReels": "فشل تحميل المقاطع",
  "noReelsAvailable": "لا توجد مقاطع متاحة",
  "checkBackLater": "تحقق لاحقًا للحصول على محتوى جديد",
  "details": "التفاصيل",
  "dealer": "تاجر",
  "individual": "فرد",
  "welcomeToDooss": "مرحبًا بك في دوس",
  "myReels": "مقاطعي",
  "noReelAvailable": "لا يوجد مقطع متاح",
  "profileUpdated": "تم تحديث الملف الشخصي",
  "editProfileStoreSuccess": "تم تعديل ملف المتجر بنجاح",
  "totalItems": "إجمالي العناصر",
  "storeViews": "مشاهدات المتجر",
  "totalSales": "إجمالي المبيعات",
  "addNewProduct": "إضافة منتج جديد",
  "addCarSuccess": "تمت إضافة السيارة بنجاح",
  "addImagePlease": "يرجى إضافة صورة",
  "addReelSuccess": "تمت إضافة المقطع بنجاح",
  "uploadVideoPlease": "يرجى رفع الفيديو",
  "editingReelSuccess": "تم تعديل المقطع بنجاح",
  "editReelError": "خطأ في تعديل المقطع",
  "productUpdatedSuccessfully": "تم تحديث المنتج بنجاح",
  "changeDataProfile": "تغيير بيانات الملف الشخصي",
  "failureEditStore": "فشل تعديل المتجر",
  "addedProduct": "تمت إضافة المنتج",
  "pleaseAddImageProduct": "يرجى إضافة صورة المنتج",
  "turkish": "التركية",
  "Turkish": "التركية",
  "noChanges": "لا يوجد تغييرات",
  "enterYourEmail": "أدخل بريدك الإلكتروني",
  "enterYourPassword": "أدخل كلمة المرور",
  "signInSuccess": "تم تسجيل الدخول بنجاح",
  "loggedOutSuccessfully": "تم تسجيل الخروج بنجاح",
  "otpSentSuccessfully": "تم إرسال رمز التحقق بنجاح",
  "otpVerifiedSuccessfully": "تم التحقق من رمز التحقق بنجاح",
  "passwordResetSuccessfully": "تم إعادة تعيين كلمة المرور بنجاح",
  "accountDeletedSuccessfully": "تم حذف الحساب بنجاح",
  "cars": "السيارات",
  "products": "المنتجات",
  "services": "الخدمات",
  "browseByType": "تصفح حسب النوع",
  "viewAll": "عرض الكل",
  "viewDetails": "عرض التفاصيل",
  "contact": "اتصل",
  "seller": "البائع",
  "market": "السوق",
  "reel": "المقطع",
  "carProducts": "منتجات السيارات",
  "carsAvailableNow": "السيارات المتاحة الآن",
  "marketReels": "مقاطع السوق",
  "nearbyCarServices": "خدمات السيارات القريبة",
  "callSeller": "اتصل بالبائع",
  "sellerNotes": "ملاحظات البائع",
  "noSellerNotesAvailable": "لا توجد ملاحظات بائع متاحة",
  "noProductsAvailable": "لا توجد منتجات متاحة",
  "checkBackLaterForNewProducts": "تحقق لاحقًا للحصول على منتجات جديدة",
  "tapToViewAll": "اضغط لعرض الكل",
  "editReel": "تعديل المقطع",
  "reelEdited": "تم تعديل المقطع",
  "reelHasBeenEditedSuccessfully": "تم تعديل المقطع بنجاح.",
  "saveEditsReel": "حفظ تعديلات المقطع",
  "addNewReel": "إضافة مقطع جديد",
  "reelAdded": "تمت إضافة المقطع",
  "sellerInformation": "معلومات البائع",
  "chats": "المحادثات",
  "noServiceAvailable": "لا توجد خدمات متاحة",
  "checkBackLaterForNewServices": "تحقق لاحقًا للحصول على خدمات جديدة"
}